README.rst
setup.py
bin/reposherlock
reposherlock/__init__.py
reposherlock/client.py
reposherlock/github.py
reposherlock.egg-info/PKG-INFO
reposherlock.egg-info/SOURCES.txt
reposherlock.egg-info/dependency_links.txt
reposherlock.egg-info/not-zip-safe
reposherlock.egg-info/requires.txt
reposherlock.egg-info/top_level.txt