Metadata-Version: 1.2
Name: reposherlock
Version: 0.1.5
Summary: RepoSherlock facilitates data retrieval from some repository management services.
Home-page: https://reposherlock.readthedocs.io/en/latest/index.html
Author: Omar Elazhary
Author-email: omazhary@gmail.com
License: MIT
Keywords: research mining repository scraper
Platform: UNKNOWN
Classifier: Development Status :: 3 - Alpha
Classifier: Intended Audience :: Science/Research
Classifier: License :: OSI Approved :: MIT License
Classifier: Natural Language :: English
Classifier: Operating System :: OS Independent
Classifier: Programming Language :: Python :: 3
Classifier: Topic :: Scientific/Engineering :: Information Analysis
Requires-Python: >=3.6
